_qlip_core_dummy_ext.cpython-310-x86_64-linux-gnu.so
qlip/__init__.py
qlip/logger.py
qlip/version.py
qlip/adapters/__init__.py
qlip/adapters/adapters.py
qlip/adapters/manager.py
qlip/analysis/__init__.py
qlip/analysis/anna_model.py
qlip/analysis/anna_module.py
qlip/analysis/base_analyser.py
qlip/analysis/base_anna.py
qlip/analysis/degradation.py
qlip/analysis/homotopy.py
qlip/analysis/homotopy_manager.py
qlip/analysis/loss.py
qlip/analysis/performance_utils.py
qlip/analysis/utils.py
qlip/analysis/optimization/__init__.py
qlip/analysis/optimization/constraint.py
qlip/analysis/optimization/expression.py
qlip/analysis/optimization/linalg_utils.py
qlip/analysis/optimization/parametrizations.py
qlip/analysis/optimization/problem.py
qlip/analysis/optimization/solver.py
qlip/analysis/optimization/variable.py
qlip/base/__init__.py
qlip/base/compiler.py
qlip/base/config.py
qlip/base/fusion.py
qlip/base/managers.py
qlip/base/observers.py
qlip/base/optimization_node.py
qlip/base/backend/__init__.py
qlip/base/backend/base_node.py
qlip/base/backend/cpu.py
qlip/base/backend/cuda.py
qlip/base/backend/mps.py
qlip/base/backend/npu.py
qlip/deploy/__init__.py
qlip/deploy/_sdpa_export_fix.py
qlip/deploy/adapters.py
qlip/deploy/base.py
qlip/deploy/compiler.py
qlip/deploy/cuda_graph.py
qlip/deploy/hf_blocks.py
qlip/deploy/onnx.py
qlip/deploy/ort.py
qlip/deploy/apple/__init__.py
qlip/deploy/apple/engine.py
qlip/deploy/apple/ane_transformers/__init__.py
qlip/deploy/apple/ane_transformers/pattern.py
qlip/deploy/apple/ane_transformers/ane_modules/__init__.py
qlip/deploy/apple/ane_transformers/ane_modules/ane_attention.py
qlip/deploy/apple/ane_transformers/ane_modules/ane_blocks.py
qlip/deploy/nvidia/__init__.py
qlip/deploy/nvidia/builder.py
qlip/deploy/nvidia/iobinders.py
qlip/deploy/nvidia/memory_allocation.py
qlip/deploy/nvidia/qconfigs.py
qlip/deploy/nvidia/session.py
qlip/deploy/nvidia/utils.py
qlip_core-0.1.2.dist-info/METADATA
qlip_core-0.1.2.dist-info/WHEEL
qlip_core-0.1.2.dist-info/top_level.txt
qlip_core-0.1.2.dist-info/RECORD
qlip_core-0.1.2.dist-info/licenses/LICENSE
