Metadata-Version: 2.4
Name: qlip.core
Version: 0.1.2
Summary: TheStage AI Full stack R&D Framework
Author-email: TheStage AI team <hello@thestage.ai>
Classifier: Programming Language :: Python :: 3
Requires-Python: >=3.10
License-File: LICENSE
Requires-Dist: torch>=2.6.0
Requires-Dist: tqdm
Requires-Dist: cvxpy
Requires-Dist: thop
Requires-Dist: scipy
Requires-Dist: packaging
Requires-Dist: numpy<2,>=1.23.5
Requires-Dist: onnx>=1.18.0
Requires-Dist: thestage-license>=0.1.4
Requires-Dist: protobuf
Requires-Dist: requests
Requires-Dist: Cython
Requires-Dist: setuptools
Provides-Extra: apple
Requires-Dist: coremltools; extra == "apple"
Requires-Dist: transformers; extra == "apple"
Provides-Extra: nvidia
Requires-Dist: tensorrt>=10.11.0; extra == "nvidia"
Requires-Dist: tensorrt-cu12>=10.11.0; extra == "nvidia"
Requires-Dist: cupy-cuda12x==13.3.0; extra == "nvidia"
Requires-Dist: cuda-python==12.8.0; extra == "nvidia"
Provides-Extra: ort
Requires-Dist: onnxruntime; extra == "ort"
Provides-Extra: tests
Requires-Dist: pytest; extra == "tests"
Dynamic: license-file
